{
  "formatVersion": 1,
  "nodes": [
    {
      "id": "0",
      "name": "Camera",
      "children": [],
      "components": [
        {
          "type": "Camera",
          "config": {
            "mode": "orthographic",
            "fov": 100,
            "orthographicScale": 22,
            "viewport": {
              "x": 0,
              "y": 0,
              "width": 1,
              "height": 1
            },
            "depth": 90,
            "nearClippingPlane": 1,
            "farClippingPlane": 1000,
            "formatVersion": 1
          },
          "id": "0"
        }
      ],
      "position": {
        "x": 0,
        "y": 1,
        "z": 2
      },
      "orientation": {
        "x": 0,
        "y": 0,
        "z": 0,
        "w": 1
      },
      "scale": {
        "x": 1,
        "y": 1,
        "z": 1
      },
      "visible": true,
      "layer": 0,
      "prefab": null
    },
    {
      "id": "19",
      "name": "Players",
      "children": [
        {
          "id": "14",
          "name": "Jimbo",
          "children": [],
          "components": [
            {
              "type": "ArcadeBody2D",
              "config": {
                "formatVersion": 2,
                "type": "box",
                "movable": true,
                "width": 1.5,
                "height": 1.8,
                "offset": {
                  "x": 0,
                  "y": 0
                },
                "bounce": {
                  "x": 0,
                  "y": 0
                },
                "tileMapAssetId": null,
                "tileSetPropertyName": null,
                "layersIndex": null
              },
              "id": "0"
            },
            {
              "type": "SpriteRenderer",
              "config": {
                "formatVersion": 1,
                "spriteAssetId": "2",
                "animationId": null,
                "horizontalFlip": false,
                "verticalFlip": false,
                "castShadow": false,
                "receiveShadow": false,
                "color": "ffffff",
                "overrideOpacity": false,
                "opacity": null,
                "materialType": "basic",
                "shaderAssetId": null
              },
              "id": "1"
            },
            {
              "type": "Behavior",
              "config": {
                "behaviorName": "PlayerBehavior",
                "propertyValues": {}
              },
              "id": "2"
            }
          ],
          "position": {
            "x": 5.694979667663574,
            "y": -0.9349966049194336,
            "z": 0
          },
          "orientation": {
            "x": 0,
            "y": 0,
            "z": 0,
            "w": 1
          },
          "scale": {
            "x": 1,
            "y": 1,
            "z": 1
          },
          "visible": true,
          "layer": 0,
          "prefab": null
        },
        {
          "id": "16",
          "name": "Jimbo2",
          "children": [],
          "components": [
            {
              "type": "ArcadeBody2D",
              "config": {
                "formatVersion": 2,
                "type": "box",
                "movable": true,
                "width": 1.5,
                "height": 1.8,
                "offset": {
                  "x": 0,
                  "y": 0
                },
                "bounce": {
                  "x": 0,
                  "y": 0
                },
                "tileMapAssetId": null,
                "tileSetPropertyName": null,
                "layersIndex": null
              },
              "id": "0"
            },
            {
              "type": "SpriteRenderer",
              "config": {
                "formatVersion": 1,
                "spriteAssetId": "2",
                "animationId": null,
                "horizontalFlip": false,
                "verticalFlip": false,
                "castShadow": false,
                "receiveShadow": false,
                "color": "ffffff",
                "overrideOpacity": false,
                "opacity": null,
                "materialType": "basic",
                "shaderAssetId": null
              },
              "id": "1"
            },
            {
              "type": "Behavior",
              "config": {
                "behaviorName": "PlayerBehavior",
                "propertyValues": {}
              },
              "id": "2"
            }
          ],
          "position": {
            "x": -8.202469825744629,
            "y": -5.05409049987793,
            "z": 0
          },
          "orientation": {
            "x": 0,
            "y": 0,
            "z": 0,
            "w": 1
          },
          "scale": {
            "x": 1,
            "y": 1,
            "z": 1
          },
          "visible": true,
          "layer": 0,
          "prefab": null
        },
        {
          "id": "17",
          "name": "Jimbo3",
          "children": [],
          "components": [
            {
              "type": "ArcadeBody2D",
              "config": {
                "formatVersion": 2,
                "type": "box",
                "movable": true,
                "width": 1.5,
                "height": 1.8,
                "offset": {
                  "x": 0,
                  "y": 0
                },
                "bounce": {
                  "x": 0,
                  "y": 0
                },
                "tileMapAssetId": null,
                "tileSetPropertyName": null,
                "layersIndex": null
              },
              "id": "0"
            },
            {
              "type": "SpriteRenderer",
              "config": {
                "formatVersion": 1,
                "spriteAssetId": "2",
                "animationId": null,
                "horizontalFlip": false,
                "verticalFlip": false,
                "castShadow": false,
                "receiveShadow": false,
                "color": "ffffff",
                "overrideOpacity": false,
                "opacity": null,
                "materialType": "basic",
                "shaderAssetId": null
              },
              "id": "1"
            },
            {
              "type": "Behavior",
              "config": {
                "behaviorName": "PlayerBehavior",
                "propertyValues": {}
              },
              "id": "2"
            }
          ],
          "position": {
            "x": -10.633951187133789,
            "y": -4.985256671905518,
            "z": 0
          },
          "orientation": {
            "x": 0,
            "y": 0,
            "z": 0,
            "w": 1
          },
          "scale": {
            "x": 1,
            "y": 1,
            "z": 1
          },
          "visible": true,
          "layer": 0,
          "prefab": null
        }
      ],
      "components": [],
      "position": {
        "x": 0,
        "y": 0,
        "z": 0
      },
      "orientation": {
        "x": 0,
        "y": 0,
        "z": 0,
        "w": 1
      },
      "scale": {
        "x": 1,
        "y": 1,
        "z": 1
      },
      "visible": true,
      "layer": 0,
      "prefab": null
    },
    {
      "id": "20",
      "name": "Ladders",
      "children": [],
      "components": [],
      "position": {
        "x": -94.147,
        "y": -37.93,
        "z": 0
      },
      "orientation": {
        "x": 0,
        "y": 0,
        "z": 0,
        "w": 1
      },
      "scale": {
        "x": 1,
        "y": 1,
        "z": 1
      },
      "visible": false,
      "layer": 0,
      "prefab": null
    },
    {
      "id": "28",
      "name": "Platforms",
      "children": [
        {
          "id": "29",
          "name": "Platform1",
          "children": [],
          "components": [
            {
              "type": "ArcadeBody2D",
              "config": {
                "formatVersion": 2,
                "type": "box",
                "movable": false,
                "width": 2,
                "height": 0.3,
                "offset": {
                  "x": 0,
                  "y": 0
                },
                "bounce": {
                  "x": 0,
                  "y": 0
                },
                "tileMapAssetId": null,
                "tileSetPropertyName": null,
                "layersIndex": null
              },
              "id": "0"
            }
          ],
          "position": {
            "x": -5.086488246917725,
            "y": 4.944561719894409,
            "z": 0
          },
          "orientation": {
            "x": 0,
            "y": 0,
            "z": 0,
            "w": 1
          },
          "scale": {
            "x": 1,
            "y": 1,
            "z": 1
          },
          "visible": true,
          "layer": 0,
          "prefab": null
        },
        {
          "id": "33",
          "name": "Platform2",
          "children": [],
          "components": [
            {
              "type": "ArcadeBody2D",
              "config": {
                "formatVersion": 2,
                "type": "box",
                "movable": false,
                "width": 2,
                "height": 0.3,
                "offset": {
                  "x": 0,
                  "y": 0
                },
                "bounce": {
                  "x": 0,
                  "y": 0
                },
                "tileMapAssetId": null,
                "tileSetPropertyName": null,
                "layersIndex": null
              },
              "id": "0"
            }
          ],
          "position": {
            "x": -0.06332111358642578,
            "y": 6.934873580932617,
            "z": 0
          },
          "orientation": {
            "x": 0,
            "y": 0,
            "z": 0,
            "w": 1
          },
          "scale": {
            "x": 1,
            "y": 1,
            "z": 1
          },
          "visible": true,
          "layer": 0,
          "prefab": null
        },
        {
          "id": "34",
          "name": "Platform3",
          "children": [],
          "components": [
            {
              "type": "ArcadeBody2D",
              "config": {
                "formatVersion": 2,
                "type": "box",
                "movable": false,
                "width": 2,
                "height": 0.3,
                "offset": {
                  "x": 0,
                  "y": 0
                },
                "bounce": {
                  "x": 0,
                  "y": 0
                },
                "tileMapAssetId": null,
                "tileSetPropertyName": null,
                "layersIndex": null
              },
              "id": "0"
            }
          ],
          "position": {
            "x": 4.940892219543457,
            "y": 8.94414073228836,
            "z": 0
          },
          "orientation": {
            "x": 0,
            "y": 0,
            "z": 0,
            "w": 1
          },
          "scale": {
            "x": 1,
            "y": 1,
            "z": 1
          },
          "visible": true,
          "layer": 0,
          "prefab": null
        },
        {
          "id": "35",
          "name": "Platform4",
          "children": [],
          "components": [
            {
              "type": "ArcadeBody2D",
              "config": {
                "formatVersion": 2,
                "type": "box",
                "movable": false,
                "width": 3,
                "height": 0.3,
                "offset": {
                  "x": 0,
                  "y": 0
                },
                "bounce": {
                  "x": 0,
                  "y": 0
                },
                "tileMapAssetId": null,
                "tileSetPropertyName": null,
                "layersIndex": null
              },
              "id": "0"
            }
          ],
          "position": {
            "x": 7.424042701721191,
            "y": 10.953407526016235,
            "z": 0
          },
          "orientation": {
            "x": 0,
            "y": 0,
            "z": 0,
            "w": 1
          },
          "scale": {
            "x": 1,
            "y": 1,
            "z": 1
          },
          "visible": true,
          "layer": 0,
          "prefab": null
        },
        {
          "id": "36",
          "name": "Platform5",
          "children": [],
          "components": [
            {
              "type": "ArcadeBody2D",
              "config": {
                "formatVersion": 2,
                "type": "box",
                "movable": false,
                "width": 3,
                "height": 0.3,
                "offset": {
                  "x": 0,
                  "y": 0
                },
                "bounce": {
                  "x": 0,
                  "y": 0
                },
                "tileMapAssetId": null,
                "tileSetPropertyName": null,
                "layersIndex": null
              },
              "id": "0"
            }
          ],
          "position": {
            "x": -0.6130256652832031,
            "y": 13.910441875457764,
            "z": 0
          },
          "orientation": {
            "x": 0,
            "y": 0,
            "z": 0,
            "w": 1
          },
          "scale": {
            "x": 1,
            "y": 1,
            "z": 1
          },
          "visible": true,
          "layer": 0,
          "prefab": null
        }
      ],
      "components": [],
      "position": {
        "x": 11.096711158752441,
        "y": -8.09357738494873,
        "z": 10
      },
      "orientation": {
        "x": 0,
        "y": 0,
        "z": 0,
        "w": 1
      },
      "scale": {
        "x": 1,
        "y": 1,
        "z": 1
      },
      "visible": true,
      "layer": 0,
      "prefab": null
    },
    {
      "id": "31",
      "name": "Dino",
      "children": [],
      "components": [
        {
          "type": "SpriteRenderer",
          "config": {
            "formatVersion": 1,
            "spriteAssetId": "27",
            "animationId": "0",
            "horizontalFlip": true,
            "verticalFlip": false,
            "castShadow": false,
            "receiveShadow": false,
            "color": "ffffff",
            "overrideOpacity": false,
            "opacity": null,
            "materialType": "basic",
            "shaderAssetId": null
          },
          "id": "0"
        },
        {
          "type": "ArcadeBody2D",
          "config": {
            "formatVersion": 2,
            "type": "box",
            "movable": false,
            "width": 2,
            "height": 1.5,
            "offset": {
              "x": 0,
              "y": -0.2
            },
            "bounce": {
              "x": 0,
              "y": 0
            },
            "tileMapAssetId": null,
            "tileSetPropertyName": null,
            "layersIndex": null
          },
          "id": "1"
        }
      ],
      "position": {
        "x": 10.512,
        "y": 6.947,
        "z": 0
      },
      "orientation": {
        "x": 0,
        "y": 0,
        "z": 0,
        "w": 1
      },
      "scale": {
        "x": 1,
        "y": 1,
        "z": 1
      },
      "visible": true,
      "layer": 0,
      "prefab": null
    },
    {
      "id": "27",
      "name": "Solids",
      "children": [
        {
          "id": "1",
          "name": "Map",
          "children": [],
          "components": [
            {
              "type": "TileMapRenderer",
              "config": {
                "tileMapAssetId": "40",
                "tileSetAssetId": null,
                "castShadow": false,
                "receiveShadow": false,
                "materialType": "basic",
                "shaderAssetId": null,
                "formatVersion": 1
              },
              "id": "0"
            },
            {
              "type": "ArcadeBody2D",
              "config": {
                "formatVersion": 2,
                "type": "tileMap",
                "movable": true,
                "width": 1,
                "height": 1,
                "offset": {
                  "x": 0,
                  "y": 0
                },
                "bounce": {
                  "x": 0,
                  "y": 0
                },
                "tileMapAssetId": "40",
                "tileSetPropertyName": null,
                "layersIndex": "0"
              },
              "id": "3"
            },
            {
              "type": "Behavior",
              "config": {
                "behaviorName": "InGameAudioBehavior",
                "propertyValues": {}
              },
              "id": "4"
            }
          ],
          "position": {
            "x": -31.097,
            "y": -1.906,
            "z": 0
          },
          "orientation": {
            "x": 0,
            "y": 0,
            "z": 0,
            "w": 1
          },
          "scale": {
            "x": 1,
            "y": 1,
            "z": 1
          },
          "visible": true,
          "layer": 0,
          "prefab": null
        }
      ],
      "components": [],
      "position": {
        "x": 11.097,
        "y": -8.094,
        "z": 0
      },
      "orientation": {
        "x": 0,
        "y": 0,
        "z": 0,
        "w": 1
      },
      "scale": {
        "x": 1,
        "y": 1,
        "z": 1
      },
      "visible": true,
      "layer": 0,
      "prefab": null
    },
    {
      "id": "37",
      "name": "Spike",
      "children": [],
      "components": [
        {
          "type": "ArcadeBody2D",
          "config": {
            "formatVersion": 2,
            "type": "box",
            "movable": true,
            "width": 1,
            "height": 1,
            "offset": {
              "x": 0,
              "y": 0
            },
            "bounce": {
              "x": 0,
              "y": 0
            },
            "tileMapAssetId": null,
            "tileSetPropertyName": null,
            "layersIndex": null
          },
          "id": "0"
        }
      ],
      "position": {
        "x": -37.81312561035156,
        "y": -15.491499900817871,
        "z": 10
      },
      "orientation": {
        "x": 0,
        "y": 0,
        "z": 0,
        "w": 1
      },
      "scale": {
        "x": 1,
        "y": 1,
        "z": 1
      },
      "visible": true,
      "layer": 0,
      "prefab": null
    },
    {
      "id": "38",
      "name": "Pit",
      "children": [],
      "components": [
        {
          "type": "ArcadeBody2D",
          "config": {
            "formatVersion": 2,
            "type": "box",
            "movable": false,
            "width": 64,
            "height": 1,
            "offset": {
              "x": 0,
              "y": 0
            },
            "bounce": {
              "x": 0,
              "y": 0
            },
            "tileMapAssetId": null,
            "tileSetPropertyName": null,
            "layersIndex": null
          },
          "id": "0"
        }
      ],
      "position": {
        "x": -1.989031195640564,
        "y": -9.505738258361816,
        "z": 10
      },
      "orientation": {
        "x": 0,
        "y": 0,
        "z": 0,
        "w": 1
      },
      "scale": {
        "x": 1,
        "y": 1,
        "z": 1
      },
      "visible": true,
      "layer": 0,
      "prefab": null
    }
  ]
}